SelfhealingAgents/__init__.py
SelfhealingAgents/listener.py
SelfhealingAgents/self_healing_system/__init__.py
SelfhealingAgents/self_healing_system/agents/__init__.py
SelfhealingAgents/self_healing_system/agents/locator_agent/__init__.py
SelfhealingAgents/self_healing_system/agents/locator_agent/base_locator_agent.py
SelfhealingAgents/self_healing_system/agents/locator_agent/browser_locator_agent.py
SelfhealingAgents/self_healing_system/agents/locator_agent/locator_agent_factory.py
SelfhealingAgents/self_healing_system/agents/locator_agent/selenium_locator_agent.py
SelfhealingAgents/self_healing_system/agents/orchestrator_agent/__init__.py
SelfhealingAgents/self_healing_system/agents/orchestrator_agent/orchestrator_agent.py
SelfhealingAgents/self_healing_system/agents/prompts/__init__.py
SelfhealingAgents/self_healing_system/agents/prompts/base_prompt_agent.py
SelfhealingAgents/self_healing_system/agents/prompts/locator/__init__.py
SelfhealingAgents/self_healing_system/agents/prompts/locator/library_specific_additions.py
SelfhealingAgents/self_healing_system/agents/prompts/locator/prompts_locator.py
SelfhealingAgents/self_healing_system/agents/prompts/orchestrator/__init__.py
SelfhealingAgents/self_healing_system/agents/prompts/orchestrator/prompts_orchestrator.py
SelfhealingAgents/self_healing_system/context_retrieving/__init__.py
SelfhealingAgents/self_healing_system/context_retrieving/dom_soap_utils.py
SelfhealingAgents/self_healing_system/context_retrieving/dom_utility_factory.py
SelfhealingAgents/self_healing_system/context_retrieving/library_dom_utils/__init__.py
SelfhealingAgents/self_healing_system/context_retrieving/library_dom_utils/appium_dom_utils.py
SelfhealingAgents/self_healing_system/context_retrieving/library_dom_utils/base_dom_utils.py
SelfhealingAgents/self_healing_system/context_retrieving/library_dom_utils/browser_dom_utils.py
SelfhealingAgents/self_healing_system/context_retrieving/library_dom_utils/selenium_dom_utils.py
robotframework_selfhealing_agents-0.1.1.dist-info/entry_points.txt
robotframework_selfhealing_agents-0.1.1.dist-info/LICENSE
robotframework_selfhealing_agents-0.1.1.dist-info/METADATA
robotframework_selfhealing_agents-0.1.1.dist-info/WHEEL
robotframework_selfhealing_agents-0.1.1.dist-info/RECORD
