Metadata-Version: 2.3
Name: robotframework-selfhealing-agents
Version: 0.1.1
Summary: 
License: Apache-2.0
Author: viadee IT-Unternehmensberatung AG
Author-email: julian.blanke@viadee.de
Requires-Python: >=3.12,<4.0
Classifier: License :: OSI Approved :: Apache Software License
Classifier: Programming Language :: Python :: 3
Classifier: Programming Language :: Python :: 3.12
Classifier: Programming Language :: Python :: 3.13
Requires-Dist: beautifulsoup4 (>=4.13.4)
Requires-Dist: lxml (>=6.0.0)
Requires-Dist: pydantic-ai-slim[azure,litellm,logfire,openai]
Requires-Dist: pydantic-settings (>=2.9.1)
Requires-Dist: python-dotenv (>=1.1.1)
Requires-Dist: robotframework (>=7.1)
Requires-Dist: robotframework-browser
Requires-Dist: robotframework-seleniumlibrary
